product_analytics/__init__.py
product_analytics/analytics.py
product_analytics-0.0.3.dist-info/METADATA
product_analytics-0.0.3.dist-info/WHEEL
product_analytics-0.0.3.dist-info/top_level.txt
product_analytics-0.0.3.dist-info/RECORD
