Metadata-Version: 2.1
Name: product-analytics
Version: 0.0.3
Summary: Segment analytics library
Home-page: https://github.com/peak-platform/product-analytics-py
Author: Peak
Author-email: will.kreitz@peak.ai
Classifier: Programming Language :: Python :: 3.7
Classifier: Programming Language :: Python :: 3.8
Classifier: Programming Language :: Python :: 3.9
Classifier: Programming Language :: Python :: 3.10
Classifier: Programming Language :: Python :: 3.11
Requires-Python: >=3.7, <4
Requires-Dist: analytics-python (>=1.2.9)
Provides-Extra: dev
Requires-Dist: black (==23.7.0) ; extra == 'dev'
Requires-Dist: pytest (==7.4.0) ; extra == 'dev'
Requires-Dist: pre-commit (==3.3.3) ; extra == 'dev'
